db_try/__init__.py
db_try/connections.py
db_try/dsn.py
db_try/py.typed
db_try/retry.py
db_try/settings.py
db_try/transaction.py
db_try-0.2.2.dist-info/WHEEL
db_try-0.2.2.dist-info/METADATA
db_try-0.2.2.dist-info/RECORD
