Metadata-Version: 2.4
Name: db-try
Version: 0.2.2
Summary: PostgreSQL and SQLAlchemy Tools
Keywords: python,postgresql,sqlalchemy
Author: community-of-python
License-Expression: MIT
Classifier: Programming Language :: Python :: 3.13
Classifier: Programming Language :: Python :: 3.14
Classifier: Typing :: Typed
Classifier: Topic :: Software Development :: Libraries
Requires-Dist: tenacity
Requires-Dist: sqlalchemy[asyncio]
Requires-Dist: asyncpg
Requires-Python: >=3.13, <4
Project-URL: repository, https://github.com/modern-python/sa-utils
